[
    {
        "date": "2025-03-01",
        "num": 764
    },
    {
        "date": "2025-03-02",
        "num": 1180
    },
    {
        "date": "2025-03-03",
        "num": 1403
    },
    {
        "date": "2025-03-04",
        "num": 2236
    },
    {
        "date": "2025-03-05",
        "num": 2679
    },
    {
        "date": "2025-03-06",
        "num": 1704
    },
    {
        "date": "2025-03-07",
        "num": 1669
    },
    {
        "date": "2025-03-08",
        "num": 1079
    },
    {
        "date": "2025-03-09",
        "num": 1087
    },
    {
        "date": "2025-03-10",
        "num": 1557
    },
    {
        "date": "2025-03-11",
        "num": 2092
    },
    {
        "date": "2025-03-12",
        "num": 2028
    },
    {
        "date": "2025-03-13",
        "num": 1516
    },
    {
        "date": "2025-03-14",
        "num": 1421
    },
    {
        "date": "2025-03-15",
        "num": 1095
    },
    {
        "date": "2025-03-16",
        "num": 826
    },
    {
        "date": "2025-03-17",
        "num": 1507
    },
    {
        "date": "2025-03-18",
        "num": 1615
    },
    {
        "date": "2025-03-19",
        "num": 1330
    },
    {
        "date": "2025-03-20",
        "num": 1253
    },
    {
        "date": "2025-03-21",
        "num": 1422
    },
    {
        "date": "2025-03-22",
        "num": 791
    },
    {
        "date": "2025-03-23",
        "num": 581
    },
    {
        "date": "2025-03-24",
        "num": 1179
    },
    {
        "date": "2025-03-25",
        "num": 1257
    },
    {
        "date": "2025-03-26",
        "num": 1267
    },
    {
        "date": "2025-03-27",
        "num": 1463
    },
    {
        "date": "2025-03-28",
        "num": 1690
    },
    {
        "date": "2025-03-29",
        "num": 1243
    },
    {
        "date": "2025-03-30",
        "num": 1130
    },
    {
        "date": "2025-03-31",
        "num": 1609
    },
    {
        "date": "2025-04-01",
        "num": 1509
    },
    {
        "date": "2025-04-02",
        "num": 2637
    },
    {
        "date": "2025-04-03",
        "num": 2709
    },
    {
        "date": "2025-04-04",
        "num": 1924
    },
    {
        "date": "2025-04-05",
        "num": 1210
    },
    {
        "date": "2025-04-06",
        "num": 1050
    },
    {
        "date": "2025-04-07",
        "num": 1785
    },
    {
        "date": "2025-04-08",
        "num": 2250
    },
    {
        "date": "2025-04-09",
        "num": 1938
    },
    {
        "date": "2025-04-10",
        "num": 1739
    },
    {
        "date": "2025-04-11",
        "num": 1289
    },
    {
        "date": "2025-04-12",
        "num": 745
    },
    {
        "date": "2025-04-13",
        "num": 793
    },
    {
        "date": "2025-04-14",
        "num": 1186
    },
    {
        "date": "2025-04-15",
        "num": 1115
    },
    {
        "date": "2025-04-16",
        "num": 1328
    },
    {
        "date": "2025-04-17",
        "num": 1302
    },
    {
        "date": "2025-04-18",
        "num": 1446
    },
    {
        "date": "2025-04-19",
        "num": 881
    },
    {
        "date": "2025-04-20",
        "num": 752
    },
    {
        "date": "2025-04-21",
        "num": 1862
    },
    {
        "date": "2025-04-22",
        "num": 1744
    },
    {
        "date": "2025-04-23",
        "num": 1746
    },
    {
        "date": "2025-04-24",
        "num": 1428
    },
    {
        "date": "2025-04-25",
        "num": 1237
    },
    {
        "date": "2025-04-26",
        "num": 1107
    },
    {
        "date": "2025-04-27",
        "num": 876
    },
    {
        "date": "2025-04-28",
        "num": 1208
    },
    {
        "date": "2025-04-29",
        "num": 1442
    },
    {
        "date": "2025-04-30",
        "num": 1429
    },
    {
        "date": "2025-05-01",
        "num": 1438
    },
    {
        "date": "2025-05-02",
        "num": 1328
    },
    {
        "date": "2025-05-03",
        "num": 778
    },
    {
        "date": "2025-05-04",
        "num": 727
    },
    {
        "date": "2025-05-05",
        "num": 1246
    },
    {
        "date": "2025-05-06",
        "num": 1008
    },
    {
        "date": "2025-05-07",
        "num": 1070
    },
    {
        "date": "2025-05-08",
        "num": 1286
    },
    {
        "date": "2025-05-09",
        "num": 1076
    },
    {
        "date": "2025-05-10",
        "num": 572
    },
    {
        "date": "2025-05-11",
        "num": 611
    },
    {
        "date": "2025-05-12",
        "num": 949
    }
]